<item>
<title>[COLOR yellow][B] Phantom of the Theatre [2016] 720p Bluray[/B][/COLOR]</title>
<urlsolve>https://drive.google.com/file/d/0BwWyhbc_5BlgenI5N2NSMDJCM1k/view</urlsolve>
<urlsolve>https://openload.co/f/8uLHTEDTWSE/[CilokMovie3]_Phantom_of_the_Theatre_[2016]_720p_Bluray.mkv.mp4</urlsolve>
<urlsolve>https://estream.to/lwlu1mim8csk.html</urlsolve>
<urlsolve>http://vidlox.tv/jdn92rhatza4</urlsolve>
<urlsolve>https://userscloud.com/134clgdkbgo4</urlsolve>
<urlsolve>https://uptobox.com/mx1gol0y6r0o</urlsolve>
<urlsolve></urlsolve>
<thumbnail>https://s20.postimg.org/v7s80cc4d/icon.png</thumbnail>
<fanart>http://img31.mtime.cn/pi/2016/04/11/100202.48118986_1000X1000.jpg</fanart>
</item>
